{
  "results": {
    "tool": {
      "name": "playwright"
    },
    "summary": {
      "tests": 67,
      "passed": 27,
      "failed": 40,
      "pending": 0,
      "skipped": 0,
      "other": 0,
      "start": 1723017438709,
      "stop": 1723019426026,
      "suites": 0
    },
    "tests": [
      {
        "name": "登入頁檢查",
        "status": "passed",
        "duration": 25244,
        "start": 1723017440,
        "stop": 1723017466,
        "rawStatus": "passed",
        "tags": [],
        "type": "e2e",
        "filePath": "C:\\Users\\luekc\\Desktop\\playwright_UI-master\\tests\\JC\\JCUItest.spec.js",
        "retries": 0,
        "flaky": false,
        "suite": "JC\\JCUItest.spec.js > @WAP JC 測試"
      },
      {
        "name": "首頁檢查",
        "status": "passed",
        "duration": 53867,
        "start": 1723017488,
        "stop": 1723017542,
        "rawStatus": "passed",
        "tags": [],
        "type": "e2e",
        "filePath": "C:\\Users\\luekc\\Desktop\\playwright_UI-master\\tests\\JC\\JCUItest.spec.js",
        "retries": 0,
        "flaky": false,
        "suite": "JC\\JCUItest.spec.js > @WAP JC 測試"
      },
      {
        "name": "首頁跑馬燈與排行榜檢查",
        "status": "passed",
        "duration": 36421,
        "start": 1723017567,
        "stop": 1723017603,
        "rawStatus": "passed",
        "tags": [],
        "type": "e2e",
        "filePath": "C:\\Users\\luekc\\Desktop\\playwright_UI-master\\tests\\JC\\JCUItest.spec.js",
        "retries": 0,
        "flaky": false,
        "suite": "JC\\JCUItest.spec.js > @WAP JC 測試"
      },
      {
        "name": "場館icon檢查",
        "status": "passed",
        "duration": 27558,
        "start": 1723017626,
        "stop": 1723017654,
        "rawStatus": "passed",
        "tags": [],
        "type": "e2e",
        "filePath": "C:\\Users\\luekc\\Desktop\\playwright_UI-master\\tests\\JC\\JCUItest.spec.js",
        "retries": 0,
        "flaky": false,
        "suite": "JC\\JCUItest.spec.js > @WAP JC 測試"
      },
      {
        "name": "真人遊戲商圖片檢查",
        "status": "passed",
        "duration": 58903,
        "start": 1723017713,
        "stop": 1723017771,
        "rawStatus": "passed",
        "tags": [],
        "type": "e2e",
        "filePath": "C:\\Users\\luekc\\Desktop\\playwright_UI-master\\tests\\JC\\JCUItest.spec.js",
        "retries": 0,
        "flaky": false,
        "suite": "JC\\JCUItest.spec.js > @WAP JC 測試"
      },
      {
        "name": "關於 Betone",
        "status": "failed",
        "duration": 100046,
        "start": 1723017440,
        "stop": 1723017540,
        "rawStatus": "timedOut",
        "tags": [],
        "type": "e2e",
        "filePath": "C:\\Users\\luekc\\Desktop\\playwright_UI-master\\tests\\MY\\MYUItest.spec.js",
        "retries": 0,
        "flaky": false,
        "suite": "MY\\MYUItest.spec.js > @WAP MY 測試"
      },
      {
        "name": "About Betone(EN)",
        "status": "failed",
        "duration": 100006,
        "start": 1723017639,
        "stop": 1723017739,
        "rawStatus": "timedOut",
        "tags": [],
        "type": "e2e",
        "filePath": "C:\\Users\\luekc\\Desktop\\playwright_UI-master\\tests\\MY\\MYUItest.spec.js",
        "retries": 0,
        "flaky": false,
        "suite": "MY\\MYUItest.spec.js > @WAP MY 測試"
      },
      {
        "name": "註冊正確流程檢查",
        "status": "failed",
        "duration": 100009,
        "start": 1723017441,
        "stop": 1723017541,
        "rawStatus": "timedOut",
        "tags": [],
        "type": "e2e",
        "filePath": "C:\\Users\\luekc\\Desktop\\playwright_UI-master\\tests\\Q0\\Q0UItest.spec.js",
        "retries": 0,
        "flaky": false,
        "suite": "Q0\\Q0UItest.spec.js > @WAP Q0 測試"
      },
      {
        "name": "註冊錯誤流程檢查",
        "status": "passed",
        "duration": 45326,
        "start": 1723017643,
        "stop": 1723017688,
        "rawStatus": "passed",
        "tags": [],
        "type": "e2e",
        "filePath": "C:\\Users\\luekc\\Desktop\\playwright_UI-master\\tests\\Q0\\Q0UItest.spec.js",
        "retries": 0,
        "flaky": false,
        "suite": "Q0\\Q0UItest.spec.js > @WAP Q0 測試"
      },
      {
        "name": "檢查關於Q0",
        "status": "failed",
        "duration": 100012,
        "start": 1723017731,
        "stop": 1723017831,
        "rawStatus": "timedOut",
        "tags": [],
        "type": "e2e",
        "filePath": "C:\\Users\\luekc\\Desktop\\playwright_UI-master\\tests\\Q0\\Q0UItest.spec.js",
        "retries": 0,
        "flaky": false,
        "suite": "Q0\\Q0UItest.spec.js > @WAP Q0 測試"
      },
      {
        "name": "檢查關於 q0 (EN)",
        "status": "failed",
        "duration": 100021,
        "start": 1723017894,
        "stop": 1723017994,
        "rawStatus": "timedOut",
        "tags": [],
        "type": "e2e",
        "filePath": "C:\\Users\\luekc\\Desktop\\playwright_UI-master\\tests\\Q0\\Q0UItest.spec.js",
        "retries": 0,
        "flaky": false,
        "suite": "Q0\\Q0UItest.spec.js > @WAP Q0 測試"
      },
      {
        "name": "Q0首頁檢查",
        "status": "passed",
        "duration": 24884,
        "start": 1723018006,
        "stop": 1723018031,
        "rawStatus": "passed",
        "tags": [],
        "type": "e2e",
        "filePath": "C:\\Users\\luekc\\Desktop\\playwright_UI-master\\tests\\Q0\\Q0UItest.spec.js",
        "retries": 0,
        "flaky": false,
        "suite": "Q0\\Q0UItest.spec.js > @WAP Q0 測試"
      },
      {
        "name": "檢查關於betone",
        "status": "passed",
        "duration": 30391,
        "start": 1723017440,
        "stop": 1723017471,
        "rawStatus": "passed",
        "tags": [],
        "type": "e2e",
        "filePath": "C:\\Users\\luekc\\Desktop\\playwright_UI-master\\tests\\Q1\\Q1UItest.spec.js",
        "retries": 0,
        "flaky": false,
        "suite": "Q1\\Q1UItest.spec.js > @WAP Q1 測試"
      },
      {
        "name": "檢查關於 betone (EN)",
        "status": "passed",
        "duration": 37152,
        "start": 1723017494,
        "stop": 1723017531,
        "rawStatus": "passed",
        "tags": [],
        "type": "e2e",
        "filePath": "C:\\Users\\luekc\\Desktop\\playwright_UI-master\\tests\\Q1\\Q1UItest.spec.js",
        "retries": 0,
        "flaky": false,
        "suite": "Q1\\Q1UItest.spec.js > @WAP Q1 測試"
      },
      {
        "name": "檢查關於 FunGame",
        "status": "passed",
        "duration": 36957,
        "start": 1723017440,
        "stop": 1723017477,
        "rawStatus": "passed",
        "tags": [],
        "type": "e2e",
        "filePath": "C:\\Users\\luekc\\Desktop\\playwright_UI-master\\tests\\Q3\\Q3UItest.spec.js",
        "retries": 0,
        "flaky": false,
        "suite": "Q3\\Q3UItest.spec.js > @WAP Q3 測試"
      },
      {
        "name": "檢查關於 FunGame (EN)",
        "status": "passed",
        "duration": 34489,
        "start": 1723017491,
        "stop": 1723017525,
        "rawStatus": "passed",
        "tags": [],
        "type": "e2e",
        "filePath": "C:\\Users\\luekc\\Desktop\\playwright_UI-master\\tests\\Q3\\Q3UItest.spec.js",
        "retries": 0,
        "flaky": false,
        "suite": "Q3\\Q3UItest.spec.js > @WAP Q3 測試"
      },
      {
        "name": "登入頁檢查",
        "status": "passed",
        "duration": 52639,
        "start": 1723017442,
        "stop": 1723017495,
        "rawStatus": "passed",
        "tags": [],
        "type": "e2e",
        "filePath": "C:\\Users\\luekc\\Desktop\\playwright_UI-master\\tests\\Q6\\Q6UItest.spec.js",
        "retries": 0,
        "flaky": false,
        "suite": "Q6\\Q6UItest.spec.js > @WAP Q6 測試"
      },
      {
        "name": "註冊頁檢查",
        "status": "passed",
        "duration": 33196,
        "start": 1723017512,
        "stop": 1723017545,
        "rawStatus": "passed",
        "tags": [],
        "type": "e2e",
        "filePath": "C:\\Users\\luekc\\Desktop\\playwright_UI-master\\tests\\Q6\\Q6UItest.spec.js",
        "retries": 0,
        "flaky": false,
        "suite": "Q6\\Q6UItest.spec.js > @WAP Q6 測試"
      },
      {
        "name": "註冊正確流程檢查",
        "status": "failed",
        "duration": 102986,
        "start": 1723017559,
        "stop": 1723017662,
        "rawStatus": "timedOut",
        "tags": [],
        "type": "e2e",
        "filePath": "C:\\Users\\luekc\\Desktop\\playwright_UI-master\\tests\\Q6\\Q6UItest.spec.js",
        "retries": 0,
        "flaky": false,
        "suite": "Q6\\Q6UItest.spec.js > @WAP Q6 測試"
      },
      {
        "name": "註冊錯誤流程檢查",
        "status": "passed",
        "duration": 67162,
        "start": 1723017808,
        "stop": 1723017875,
        "rawStatus": "passed",
        "tags": [],
        "type": "e2e",
        "filePath": "C:\\Users\\luekc\\Desktop\\playwright_UI-master\\tests\\Q6\\Q6UItest.spec.js",
        "retries": 0,
        "flaky": false,
        "suite": "Q6\\Q6UItest.spec.js > @WAP Q6 測試"
      },
      {
        "name": "首頁體育下注(注额15)",
        "status": "failed",
        "duration": 100016,
        "start": 1723017899,
        "stop": 1723017999,
        "rawStatus": "timedOut",
        "tags": [],
        "type": "e2e",
        "filePath": "C:\\Users\\luekc\\Desktop\\playwright_UI-master\\tests\\Q6\\Q6UItest.spec.js",
        "retries": 0,
        "flaky": false,
        "suite": "Q6\\Q6UItest.spec.js > @WAP Q6 測試"
      },
      {
        "name": "檢查首頁",
        "status": "failed",
        "duration": 27082,
        "start": 1723018027,
        "stop": 1723018054,
        "message": "Error: \u001b[2mexpect(\u001b[22m\u001b[31mreceived\u001b[39m\u001b[2m).\u001b[22mtoBe\u001b[2m(\u001b[22m\u001b[32mexpected\u001b[39m\u001b[2m) // Object.is equality\u001b[22m\n\nExpected: \u001b[32m0\u001b[39m\nReceived: \u001b[31m2\u001b[39m",
        "trace": "Error: \u001b[2mexpect(\u001b[22m\u001b[31mreceived\u001b[39m\u001b[2m).\u001b[22mtoBe\u001b[2m(\u001b[22m\u001b[32mexpected\u001b[39m\u001b[2m) // Object.is equality\u001b[22m\n\nExpected: \u001b[32m0\u001b[39m\nReceived: \u001b[31m2\u001b[39m\n    at C:\\Users\\luekc\\Desktop\\playwright_UI-master\\tests\\Q6\\Q6UItest.spec.js:667:40",
        "rawStatus": "failed",
        "tags": [],
        "type": "e2e",
        "filePath": "C:\\Users\\luekc\\Desktop\\playwright_UI-master\\tests\\Q6\\Q6UItest.spec.js",
        "retries": 0,
        "flaky": false,
        "suite": "Q6\\Q6UItest.spec.js > @WAP Q6 測試"
      },
      {
        "name": "檢查娛樂城",
        "status": "failed",
        "duration": 45682,
        "start": 1723018056,
        "stop": 1723018102,
        "message": "Error: \u001b[2mexpect(\u001b[22m\u001b[31mreceived\u001b[39m\u001b[2m).\u001b[22mtoBe\u001b[2m(\u001b[22m\u001b[32mexpected\u001b[39m\u001b[2m) // Object.is equality\u001b[22m\n\nExpected: \u001b[32m0\u001b[39m\nReceived: \u001b[31m3\u001b[39m",
        "trace": "Error: \u001b[2mexpect(\u001b[22m\u001b[31mreceived\u001b[39m\u001b[2m).\u001b[22mtoBe\u001b[2m(\u001b[22m\u001b[32mexpected\u001b[39m\u001b[2m) // Object.is equality\u001b[22m\n\nExpected: \u001b[32m0\u001b[39m\nReceived: \u001b[31m3\u001b[39m\n    at C:\\Users\\luekc\\Desktop\\playwright_UI-master\\tests\\Q6\\Q6UItest.spec.js:846:35",
        "rawStatus": "failed",
        "tags": [],
        "type": "e2e",
        "filePath": "C:\\Users\\luekc\\Desktop\\playwright_UI-master\\tests\\Q6\\Q6UItest.spec.js",
        "retries": 0,
        "flaky": false,
        "suite": "Q6\\Q6UItest.spec.js > @WAP Q6 測試"
      },
      {
        "name": "檢查個人頁icon圖片",
        "status": "failed",
        "duration": 26222,
        "start": 1723018112,
        "stop": 1723018139,
        "message": "Error: 以下是檢測到的錯誤: 優惠活動 圖標不存在, 加入我們 圖標不存在, 返水領取 圖標不存在, VIP福利 圖標不存在, 每日盈虧數據 圖標不存在, 充提記錄 圖標不存在, 錢包交易紀錄 圖標不存在, 綁定銀行卡 圖標不存在, 遊戲投注數據 圖標不存在, 推薦好友 圖標不存在, 好友推廣鏈結 圖標不存在, 賽果查詢 圖標不存在, 語言選擇 圖標不存在\n\n\u001b[2mexpect(\u001b[22m\u001b[31mreceived\u001b[39m\u001b[2m).\u001b[22mtoBe\u001b[2m(\u001b[22m\u001b[32mexpected\u001b[39m\u001b[2m) // Object.is equality\u001b[22m\n\nExpected: \u001b[32m0\u001b[39m\nReceived: \u001b[31m13\u001b[39m",
        "trace": "Error: 以下是檢測到的錯誤: 優惠活動 圖標不存在, 加入我們 圖標不存在, 返水領取 圖標不存在, VIP福利 圖標不存在, 每日盈虧數據 圖標不存在, 充提記錄 圖標不存在, 錢包交易紀錄 圖標不存在, 綁定銀行卡 圖標不存在, 遊戲投注數據 圖標不存在, 推薦好友 圖標不存在, 好友推廣鏈結 圖標不存在, 賽果查詢 圖標不存在, 語言選擇 圖標不存在\n\n\u001b[2mexpect(\u001b[22m\u001b[31mreceived\u001b[39m\u001b[2m).\u001b[22mtoBe\u001b[2m(\u001b[22m\u001b[32mexpected\u001b[39m\u001b[2m) // Object.is equality\u001b[22m\n\nExpected: \u001b[32m0\u001b[39m\nReceived: \u001b[31m13\u001b[39m\n    at C:\\Users\\luekc\\Desktop\\playwright_UI-master\\tests\\Q6\\Q6UItest.spec.js:949:66",
        "rawStatus": "failed",
        "tags": [],
        "type": "e2e",
        "filePath": "C:\\Users\\luekc\\Desktop\\playwright_UI-master\\tests\\Q6\\Q6UItest.spec.js",
        "retries": 0,
        "flaky": false,
        "suite": "Q6\\Q6UItest.spec.js > @WAP Q6 測試"
      },
      {
        "name": "檢查個人頁並點擊各個鏈接",
        "status": "failed",
        "duration": 28341,
        "start": 1723018152,
        "stop": 1723018181,
        "message": "Error: 以下標籤未找到或鏈接點擊跳轉後報錯: uitest001, VIP, 錢包餘額, 上次提款金額, 優惠申請大廳, 錢包中心, 存款, 提款, 加入我們, 返水領取, VIP福利, 每日盈虧數據, 充提記錄, 錢包交易紀錄, 綁定銀行卡, 遊戲投注數據, 推廣鏈結, 推薦好友, 好友推廣鏈結, 賽果查詢, 語言選擇\n\n\u001b[2mexpect(\u001b[22m\u001b[31mreceived\u001b[39m\u001b[2m).\u001b[22mtoBe\u001b[2m(\u001b[22m\u001b[32mexpected\u001b[39m\u001b[2m) // Object.is equality\u001b[22m\n\nExpected: \u001b[32m0\u001b[39m\nReceived: \u001b[31m21\u001b[39m",
        "trace": "Error: 以下標籤未找到或鏈接點擊跳轉後報錯: uitest001, VIP, 錢包餘額, 上次提款金額, 優惠申請大廳, 錢包中心, 存款, 提款, 加入我們, 返水領取, VIP福利, 每日盈虧數據, 充提記錄, 錢包交易紀錄, 綁定銀行卡, 遊戲投注數據, 推廣鏈結, 推薦好友, 好友推廣鏈結, 賽果查詢, 語言選擇\n\n\u001b[2mexpect(\u001b[22m\u001b[31mreceived\u001b[39m\u001b[2m).\u001b[22mtoBe\u001b[2m(\u001b[22m\u001b[32mexpected\u001b[39m\u001b[2m) // Object.is equality\u001b[22m\n\nExpected: \u001b[32m0\u001b[39m\nReceived: \u001b[31m21\u001b[39m\n    at C:\\Users\\luekc\\Desktop\\playwright_UI-master\\tests\\Q6\\Q6UItest.spec.js:1069:68",
        "rawStatus": "failed",
        "tags": [],
        "type": "e2e",
        "filePath": "C:\\Users\\luekc\\Desktop\\playwright_UI-master\\tests\\Q6\\Q6UItest.spec.js",
        "retries": 0,
        "flaky": false,
        "suite": "Q6\\Q6UItest.spec.js > @WAP Q6 測試"
      },
      {
        "name": "檢查個人頁並點擊錢包中心",
        "status": "failed",
        "duration": 100005,
        "start": 1723018198,
        "stop": 1723018298,
        "rawStatus": "timedOut",
        "tags": [],
        "type": "e2e",
        "filePath": "C:\\Users\\luekc\\Desktop\\playwright_UI-master\\tests\\Q6\\Q6UItest.spec.js",
        "retries": 0,
        "flaky": false,
        "suite": "Q6\\Q6UItest.spec.js > @WAP Q6 測試"
      },
      {
        "name": "檢查關於港體會",
        "status": "failed",
        "duration": 100019,
        "start": 1723018304,
        "stop": 1723018404,
        "rawStatus": "timedOut",
        "tags": [],
        "type": "e2e",
        "filePath": "C:\\Users\\luekc\\Desktop\\playwright_UI-master\\tests\\Q6\\Q6UItest.spec.js",
        "retries": 0,
        "flaky": false,
        "suite": "Q6\\Q6UItest.spec.js > @WAP Q6 測試"
      },
      {
        "name": "檢查走地頁",
        "status": "failed",
        "duration": 100011,
        "start": 1723018414,
        "stop": 1723018514,
        "rawStatus": "timedOut",
        "tags": [],
        "type": "e2e",
        "filePath": "C:\\Users\\luekc\\Desktop\\playwright_UI-master\\tests\\Q6\\Q6UItest.spec.js",
        "retries": 0,
        "flaky": false,
        "suite": "Q6\\Q6UItest.spec.js > @WAP Q6 測試"
      },
      {
        "name": "登入頁檢查(EN)",
        "status": "passed",
        "duration": 21080,
        "start": 1723018524,
        "stop": 1723018545,
        "rawStatus": "passed",
        "tags": [],
        "type": "e2e",
        "filePath": "C:\\Users\\luekc\\Desktop\\playwright_UI-master\\tests\\Q6\\Q6UItest.spec.js",
        "retries": 0,
        "flaky": false,
        "suite": "Q6\\Q6UItest.spec.js > @WAP Q6 測試"
      },
      {
        "name": "註冊頁檢查(EN)",
        "status": "passed",
        "duration": 19453,
        "start": 1723018554,
        "stop": 1723018574,
        "rawStatus": "passed",
        "tags": [],
        "type": "e2e",
        "filePath": "C:\\Users\\luekc\\Desktop\\playwright_UI-master\\tests\\Q6\\Q6UItest.spec.js",
        "retries": 0,
        "flaky": false,
        "suite": "Q6\\Q6UItest.spec.js > @WAP Q6 測試"
      },
      {
        "name": "首頁檢查(EN)",
        "status": "failed",
        "duration": 33053,
        "start": 1723018580,
        "stop": 1723018613,
        "message": "Error: \u001b[2mexpect(\u001b[22m\u001b[31mreceived\u001b[39m\u001b[2m).\u001b[22mtoBe\u001b[2m(\u001b[22m\u001b[32mexpected\u001b[39m\u001b[2m) // Object.is equality\u001b[22m\n\nExpected: \u001b[32m0\u001b[39m\nReceived: \u001b[31m2\u001b[39m",
        "trace": "Error: \u001b[2mexpect(\u001b[22m\u001b[31mreceived\u001b[39m\u001b[2m).\u001b[22mtoBe\u001b[2m(\u001b[22m\u001b[32mexpected\u001b[39m\u001b[2m) // Object.is equality\u001b[22m\n\nExpected: \u001b[32m0\u001b[39m\nReceived: \u001b[31m2\u001b[39m\n    at C:\\Users\\luekc\\Desktop\\playwright_UI-master\\tests\\Q6\\Q6UItest.spec.js:1870:31",
        "rawStatus": "failed",
        "tags": [],
        "type": "e2e",
        "filePath": "C:\\Users\\luekc\\Desktop\\playwright_UI-master\\tests\\Q6\\Q6UItest.spec.js",
        "retries": 0,
        "flaky": false,
        "suite": "Q6\\Q6UItest.spec.js > @WAP Q6 測試"
      },
      {
        "name": "檢查娛樂城(EN)",
        "status": "failed",
        "duration": 36943,
        "start": 1723018625,
        "stop": 1723018661,
        "message": "Error: \u001b[2mexpect(\u001b[22m\u001b[31mreceived\u001b[39m\u001b[2m).\u001b[22mtoBeTruthy\u001b[2m()\u001b[22m\n\nReceived: \u001b[31mfalse\u001b[39m",
        "trace": "Error: \u001b[2mexpect(\u001b[22m\u001b[31mreceived\u001b[39m\u001b[2m).\u001b[22mtoBeTruthy\u001b[2m()\u001b[22m\n\nReceived: \u001b[31mfalse\u001b[39m\n    at C:\\Users\\luekc\\Desktop\\playwright_UI-master\\tests\\Q6\\Q6UItest.spec.js:1989:35",
        "rawStatus": "failed",
        "tags": [],
        "type": "e2e",
        "filePath": "C:\\Users\\luekc\\Desktop\\playwright_UI-master\\tests\\Q6\\Q6UItest.spec.js",
        "retries": 0,
        "flaky": false,
        "suite": "Q6\\Q6UItest.spec.js > @WAP Q6 測試"
      },
      {
        "name": "檢查個人頁並點擊各個鏈接(EN)",
        "status": "failed",
        "duration": 29717,
        "start": 1723018684,
        "stop": 1723018714,
        "message": "Error: 以下標籤未找到: uitest001, VIP, Balance, Recent Withdraw, Task Center, Wallet, Deposit, Withdraw, Join us, Rebate, VIP, Profit, Deposit & Withdrawal, Transaction Record, Bank Card Management, Bet History, Recommend friends, Friend promotion link, Game Result, Language Selection\n\n\u001b[2mexpect(\u001b[22m\u001b[31mreceived\u001b[39m\u001b[2m).\u001b[22mtoBe\u001b[2m(\u001b[22m\u001b[32mexpected\u001b[39m\u001b[2m) // Object.is equality\u001b[22m\n\nExpected: \u001b[32m0\u001b[39m\nReceived: \u001b[31m20\u001b[39m",
        "trace": "Error: 以下標籤未找到: uitest001, VIP, Balance, Recent Withdraw, Task Center, Wallet, Deposit, Withdraw, Join us, Rebate, VIP, Profit, Deposit & Withdrawal, Transaction Record, Bank Card Management, Bet History, Recommend friends, Friend promotion link, Game Result, Language Selection\n\n\u001b[2mexpect(\u001b[22m\u001b[31mreceived\u001b[39m\u001b[2m).\u001b[22mtoBe\u001b[2m(\u001b[22m\u001b[32mexpected\u001b[39m\u001b[2m) // Object.is equality\u001b[22m\n\nExpected: \u001b[32m0\u001b[39m\nReceived: \u001b[31m20\u001b[39m\n    at C:\\Users\\luekc\\Desktop\\playwright_UI-master\\tests\\Q6\\Q6UItest.spec.js:2208:90",
        "rawStatus": "failed",
        "tags": [],
        "type": "e2e",
        "filePath": "C:\\Users\\luekc\\Desktop\\playwright_UI-master\\tests\\Q6\\Q6UItest.spec.js",
        "retries": 0,
        "flaky": false,
        "suite": "Q6\\Q6UItest.spec.js > @WAP Q6 測試"
      },
      {
        "name": "檢查個人頁icon圖片(EN)",
        "status": "failed",
        "duration": 14572,
        "start": 1723018732,
        "stop": 1723018746,
        "message": "Error: \u001b[2mexpect(\u001b[22m\u001b[31mreceived\u001b[39m\u001b[2m).\u001b[22mtoBe\u001b[2m(\u001b[22m\u001b[32mexpected\u001b[39m\u001b[2m) // Object.is equality\u001b[22m\n\nExpected: \u001b[32mtrue\u001b[39m\nReceived: \u001b[31mfalse\u001b[39m",
        "trace": "Error: \u001b[2mexpect(\u001b[22m\u001b[31mreceived\u001b[39m\u001b[2m).\u001b[22mtoBe\u001b[2m(\u001b[22m\u001b[32mexpected\u001b[39m\u001b[2m) // Object.is equality\u001b[22m\n\nExpected: \u001b[32mtrue\u001b[39m\nReceived: \u001b[31mfalse\u001b[39m\n    at C:\\Users\\luekc\\Desktop\\playwright_UI-master\\tests\\Q6\\Q6UItest.spec.js:2295:32",
        "rawStatus": "failed",
        "tags": [],
        "type": "e2e",
        "filePath": "C:\\Users\\luekc\\Desktop\\playwright_UI-master\\tests\\Q6\\Q6UItest.spec.js",
        "retries": 0,
        "flaky": false,
        "suite": "Q6\\Q6UItest.spec.js > @WAP Q6 測試"
      },
      {
        "name": "檢查關於港體會(EN)",
        "status": "failed",
        "duration": 100008,
        "start": 1723018751,
        "stop": 1723018851,
        "rawStatus": "timedOut",
        "tags": [],
        "type": "e2e",
        "filePath": "C:\\Users\\luekc\\Desktop\\playwright_UI-master\\tests\\Q6\\Q6UItest.spec.js",
        "retries": 0,
        "flaky": false,
        "suite": "Q6\\Q6UItest.spec.js > @WAP Q6 測試"
      },
      {
        "name": "登入頁檢查",
        "status": "passed",
        "duration": 42295,
        "start": 1723017442,
        "stop": 1723017484,
        "rawStatus": "passed",
        "tags": [],
        "type": "e2e",
        "filePath": "C:\\Users\\luekc\\Desktop\\playwright_UI-master\\tests\\Q8\\Q8UItest.spec.js",
        "retries": 0,
        "flaky": false,
        "suite": "Q8\\Q8UItest.spec.js > @WAP Q8 測試"
      },
      {
        "name": "註冊頁檢查",
        "status": "passed",
        "duration": 52729,
        "start": 1723017497,
        "stop": 1723017549,
        "rawStatus": "passed",
        "tags": [],
        "type": "e2e",
        "filePath": "C:\\Users\\luekc\\Desktop\\playwright_UI-master\\tests\\Q8\\Q8UItest.spec.js",
        "retries": 0,
        "flaky": false,
        "suite": "Q8\\Q8UItest.spec.js > @WAP Q8 測試"
      },
      {
        "name": "註冊正確流程檢查",
        "status": "failed",
        "duration": 100023,
        "start": 1723017559,
        "stop": 1723017659,
        "rawStatus": "timedOut",
        "tags": [],
        "type": "e2e",
        "filePath": "C:\\Users\\luekc\\Desktop\\playwright_UI-master\\tests\\Q8\\Q8UItest.spec.js",
        "retries": 0,
        "flaky": false,
        "suite": "Q8\\Q8UItest.spec.js > @WAP Q8 測試"
      },
      {
        "name": "註冊錯誤流程檢查",
        "status": "passed",
        "duration": 43435,
        "start": 1723017788,
        "stop": 1723017832,
        "rawStatus": "passed",
        "tags": [],
        "type": "e2e",
        "filePath": "C:\\Users\\luekc\\Desktop\\playwright_UI-master\\tests\\Q8\\Q8UItest.spec.js",
        "retries": 0,
        "flaky": false,
        "suite": "Q8\\Q8UItest.spec.js > @WAP Q8 測試"
      },
      {
        "name": "首頁體育下注(注额15)",
        "status": "failed",
        "duration": 100017,
        "start": 1723017855,
        "stop": 1723017955,
        "rawStatus": "timedOut",
        "tags": [],
        "type": "e2e",
        "filePath": "C:\\Users\\luekc\\Desktop\\playwright_UI-master\\tests\\Q8\\Q8UItest.spec.js",
        "retries": 0,
        "flaky": false,
        "suite": "Q8\\Q8UItest.spec.js > @WAP Q8 測試"
      },
      {
        "name": "檢查首頁",
        "status": "failed",
        "duration": 28173,
        "start": 1723017964,
        "stop": 1723017992,
        "message": "Error: \u001b[2mexpect(\u001b[22m\u001b[31mreceived\u001b[39m\u001b[2m).\u001b[22mtoBe\u001b[2m(\u001b[22m\u001b[32mexpected\u001b[39m\u001b[2m) // Object.is equality\u001b[22m\n\nExpected: \u001b[32m0\u001b[39m\nReceived: \u001b[31m2\u001b[39m",
        "trace": "Error: \u001b[2mexpect(\u001b[22m\u001b[31mreceived\u001b[39m\u001b[2m).\u001b[22mtoBe\u001b[2m(\u001b[22m\u001b[32mexpected\u001b[39m\u001b[2m) // Object.is equality\u001b[22m\n\nExpected: \u001b[32m0\u001b[39m\nReceived: \u001b[31m2\u001b[39m\n    at C:\\Users\\luekc\\Desktop\\playwright_UI-master\\tests\\Q8\\Q8UItest.spec.js:661:40",
        "rawStatus": "failed",
        "tags": [],
        "type": "e2e",
        "filePath": "C:\\Users\\luekc\\Desktop\\playwright_UI-master\\tests\\Q8\\Q8UItest.spec.js",
        "retries": 0,
        "flaky": false,
        "suite": "Q8\\Q8UItest.spec.js > @WAP Q8 測試"
      },
      {
        "name": "檢查娛樂城",
        "status": "failed",
        "duration": 25962,
        "start": 1723018002,
        "stop": 1723018028,
        "message": "Error: 未找到每日簽到文字\n\n\u001b[2mexpect(\u001b[22m\u001b[31mreceived\u001b[39m\u001b[2m).\u001b[22mtoBeTruthy\u001b[2m()\u001b[22m\n\nReceived: \u001b[31mfalse\u001b[39m",
        "trace": "Error: 未找到每日簽到文字\n\n\u001b[2mexpect(\u001b[22m\u001b[31mreceived\u001b[39m\u001b[2m).\u001b[22mtoBeTruthy\u001b[2m()\u001b[22m\n\nReceived: \u001b[31mfalse\u001b[39m\n    at C:\\Users\\luekc\\Desktop\\playwright_UI-master\\tests\\Q8\\Q8UItest.spec.js:755:48",
        "rawStatus": "failed",
        "tags": [],
        "type": "e2e",
        "filePath": "C:\\Users\\luekc\\Desktop\\playwright_UI-master\\tests\\Q8\\Q8UItest.spec.js",
        "retries": 0,
        "flaky": false,
        "suite": "Q8\\Q8UItest.spec.js > @WAP Q8 測試"
      },
      {
        "name": "檢查個人頁icon圖片",
        "status": "failed",
        "duration": 12215,
        "start": 1723018032,
        "stop": 1723018044,
        "message": "Error: 以下是检测到的错误: 優惠活動 图标不存在, 加入我們 图标不存在, 返水領取 图标不存在, VIP福利 图标不存在, 每日盈虧數據 图标不存在, 充提記錄 图标不存在, 錢包交易紀錄 图标不存在, 綁定銀行卡 图标不存在, 遊戲投注數據 图标不存在, 賽果查詢 图标不存在, 語言選擇 图标不存在\n\n\u001b[2mexpect(\u001b[22m\u001b[31mreceived\u001b[39m\u001b[2m).\u001b[22mtoBe\u001b[2m(\u001b[22m\u001b[32mexpected\u001b[39m\u001b[2m) // Object.is equality\u001b[22m\n\nExpected: \u001b[32m0\u001b[39m\nReceived: \u001b[31m11\u001b[39m",
        "trace": "Error: 以下是检测到的错误: 優惠活動 图标不存在, 加入我們 图标不存在, 返水領取 图标不存在, VIP福利 图标不存在, 每日盈虧數據 图标不存在, 充提記錄 图标不存在, 錢包交易紀錄 图标不存在, 綁定銀行卡 图标不存在, 遊戲投注數據 图标不存在, 賽果查詢 图标不存在, 語言選擇 图标不存在\n\n\u001b[2mexpect(\u001b[22m\u001b[31mreceived\u001b[39m\u001b[2m).\u001b[22mtoBe\u001b[2m(\u001b[22m\u001b[32mexpected\u001b[39m\u001b[2m) // Object.is equality\u001b[22m\n\nExpected: \u001b[32m0\u001b[39m\nReceived: \u001b[31m11\u001b[39m\n    at C:\\Users\\luekc\\Desktop\\playwright_UI-master\\tests\\Q8\\Q8UItest.spec.js:870:66",
        "rawStatus": "failed",
        "tags": [],
        "type": "e2e",
        "filePath": "C:\\Users\\luekc\\Desktop\\playwright_UI-master\\tests\\Q8\\Q8UItest.spec.js",
        "retries": 0,
        "flaky": false,
        "suite": "Q8\\Q8UItest.spec.js > @WAP Q8 測試"
      },
      {
        "name": "檢查個人頁並點擊各個鏈接",
        "status": "failed",
        "duration": 9338,
        "start": 1723018047,
        "stop": 1723018056,
        "message": "Error: 以下標籤未找到或鏈接點擊跳轉後報錯: uitest001, VIP, 錢包餘額, 上次提款金額, 優惠申請大廳, 錢包中心, 存款, 提款, 返水領取, VIP福利, 每日盈虧數據, 充提記錄, 錢包交易紀錄, 綁定銀行卡, 遊戲投注數據, 賽果查詢, 語言選擇\n\n\u001b[2mexpect(\u001b[22m\u001b[31mreceived\u001b[39m\u001b[2m).\u001b[22mtoBe\u001b[2m(\u001b[22m\u001b[32mexpected\u001b[39m\u001b[2m) // Object.is equality\u001b[22m\n\nExpected: \u001b[32m0\u001b[39m\nReceived: \u001b[31m17\u001b[39m",
        "trace": "Error: 以下標籤未找到或鏈接點擊跳轉後報錯: uitest001, VIP, 錢包餘額, 上次提款金額, 優惠申請大廳, 錢包中心, 存款, 提款, 返水領取, VIP福利, 每日盈虧數據, 充提記錄, 錢包交易紀錄, 綁定銀行卡, 遊戲投注數據, 賽果查詢, 語言選擇\n\n\u001b[2mexpect(\u001b[22m\u001b[31mreceived\u001b[39m\u001b[2m).\u001b[22mtoBe\u001b[2m(\u001b[22m\u001b[32mexpected\u001b[39m\u001b[2m) // Object.is equality\u001b[22m\n\nExpected: \u001b[32m0\u001b[39m\nReceived: \u001b[31m17\u001b[39m\n    at C:\\Users\\luekc\\Desktop\\playwright_UI-master\\tests\\Q8\\Q8UItest.spec.js:990:68",
        "rawStatus": "failed",
        "tags": [],
        "type": "e2e",
        "filePath": "C:\\Users\\luekc\\Desktop\\playwright_UI-master\\tests\\Q8\\Q8UItest.spec.js",
        "retries": 0,
        "flaky": false,
        "suite": "Q8\\Q8UItest.spec.js > @WAP Q8 測試"
      },
      {
        "name": "檢查個人頁並點擊錢包中心",
        "status": "failed",
        "duration": 100003,
        "start": 1723018065,
        "stop": 1723018165,
        "rawStatus": "timedOut",
        "tags": [],
        "type": "e2e",
        "filePath": "C:\\Users\\luekc\\Desktop\\playwright_UI-master\\tests\\Q8\\Q8UItest.spec.js",
        "retries": 0,
        "flaky": false,
        "suite": "Q8\\Q8UItest.spec.js > @WAP Q8 測試"
      },
      {
        "name": "檢查個人頁並點擊存款",
        "status": "failed",
        "duration": 100011,
        "start": 1723018190,
        "stop": 1723018290,
        "rawStatus": "timedOut",
        "tags": [],
        "type": "e2e",
        "filePath": "C:\\Users\\luekc\\Desktop\\playwright_UI-master\\tests\\Q8\\Q8UItest.spec.js",
        "retries": 0,
        "flaky": false,
        "suite": "Q8\\Q8UItest.spec.js > @WAP Q8 測試"
      },
      {
        "name": "檢查關於樂古娛樂",
        "status": "failed",
        "duration": 100014,
        "start": 1723018303,
        "stop": 1723018403,
        "rawStatus": "timedOut",
        "tags": [],
        "type": "e2e",
        "filePath": "C:\\Users\\luekc\\Desktop\\playwright_UI-master\\tests\\Q8\\Q8UItest.spec.js",
        "retries": 0,
        "flaky": false,
        "suite": "Q8\\Q8UItest.spec.js > @WAP Q8 測試"
      },
      {
        "name": "檢查走地頁",
        "status": "failed",
        "duration": 100014,
        "start": 1723018413,
        "stop": 1723018513,
        "rawStatus": "timedOut",
        "tags": [],
        "type": "e2e",
        "filePath": "C:\\Users\\luekc\\Desktop\\playwright_UI-master\\tests\\Q8\\Q8UItest.spec.js",
        "retries": 0,
        "flaky": false,
        "suite": "Q8\\Q8UItest.spec.js > @WAP Q8 測試"
      },
      {
        "name": "登入頁檢查(EN)",
        "status": "passed",
        "duration": 12354,
        "start": 1723018524,
        "stop": 1723018536,
        "rawStatus": "passed",
        "tags": [],
        "type": "e2e",
        "filePath": "C:\\Users\\luekc\\Desktop\\playwright_UI-master\\tests\\Q8\\Q8UItest.spec.js",
        "retries": 0,
        "flaky": false,
        "suite": "Q8\\Q8UItest.spec.js > @WAP Q8 測試"
      },
      {
        "name": "註冊頁檢查(EN)",
        "status": "passed",
        "duration": 8803,
        "start": 1723018539,
        "stop": 1723018547,
        "rawStatus": "passed",
        "tags": [],
        "type": "e2e",
        "filePath": "C:\\Users\\luekc\\Desktop\\playwright_UI-master\\tests\\Q8\\Q8UItest.spec.js",
        "retries": 0,
        "flaky": false,
        "suite": "Q8\\Q8UItest.spec.js > @WAP Q8 測試"
      },
      {
        "name": "首頁檢查(EN)",
        "status": "failed",
        "duration": 19156,
        "start": 1723018551,
        "stop": 1723018571,
        "message": "Error: \u001b[2mexpect(\u001b[22m\u001b[31mreceived\u001b[39m\u001b[2m).\u001b[22mtoBe\u001b[2m(\u001b[22m\u001b[32mexpected\u001b[39m\u001b[2m) // Object.is equality\u001b[22m\n\nExpected: \u001b[32m0\u001b[39m\nReceived: \u001b[31m2\u001b[39m",
        "trace": "Error: \u001b[2mexpect(\u001b[22m\u001b[31mreceived\u001b[39m\u001b[2m).\u001b[22mtoBe\u001b[2m(\u001b[22m\u001b[32mexpected\u001b[39m\u001b[2m) // Object.is equality\u001b[22m\n\nExpected: \u001b[32m0\u001b[39m\nReceived: \u001b[31m2\u001b[39m\n    at C:\\Users\\luekc\\Desktop\\playwright_UI-master\\tests\\Q8\\Q8UItest.spec.js:1733:31",
        "rawStatus": "failed",
        "tags": [],
        "type": "e2e",
        "filePath": "C:\\Users\\luekc\\Desktop\\playwright_UI-master\\tests\\Q8\\Q8UItest.spec.js",
        "retries": 0,
        "flaky": false,
        "suite": "Q8\\Q8UItest.spec.js > @WAP Q8 測試"
      },
      {
        "name": "檢查娛樂城(EN)",
        "status": "failed",
        "duration": 19363,
        "start": 1723018579,
        "stop": 1723018598,
        "message": "Error: \u001b[2mexpect(\u001b[22m\u001b[31mreceived\u001b[39m\u001b[2m).\u001b[22mtoBeTruthy\u001b[2m()\u001b[22m\n\nReceived: \u001b[31mfalse\u001b[39m",
        "trace": "Error: \u001b[2mexpect(\u001b[22m\u001b[31mreceived\u001b[39m\u001b[2m).\u001b[22mtoBeTruthy\u001b[2m()\u001b[22m\n\nReceived: \u001b[31mfalse\u001b[39m\n    at C:\\Users\\luekc\\Desktop\\playwright_UI-master\\tests\\Q8\\Q8UItest.spec.js:1846:35",
        "rawStatus": "failed",
        "tags": [],
        "type": "e2e",
        "filePath": "C:\\Users\\luekc\\Desktop\\playwright_UI-master\\tests\\Q8\\Q8UItest.spec.js",
        "retries": 0,
        "flaky": false,
        "suite": "Q8\\Q8UItest.spec.js > @WAP Q8 測試"
      },
      {
        "name": "檢查個人頁並點擊各個鏈接(EN)",
        "status": "failed",
        "duration": 19275,
        "start": 1723018611,
        "stop": 1723018630,
        "message": "Error: 以下標籤未找到: uitest001, VIP, Balance, Recent Withdraw, Task Center, Wallet, Deposit, Withdraw, Rebate, VIP, Profit, Deposit & Withdrawal, Transaction Record, Bank Card Management, Bet History, Game Result, Language Selection, Join us\n\n\u001b[2mexpect(\u001b[22m\u001b[31mreceived\u001b[39m\u001b[2m).\u001b[22mtoBe\u001b[2m(\u001b[22m\u001b[32mexpected\u001b[39m\u001b[2m) // Object.is equality\u001b[22m\n\nExpected: \u001b[32m0\u001b[39m\nReceived: \u001b[31m18\u001b[39m",
        "trace": "Error: 以下標籤未找到: uitest001, VIP, Balance, Recent Withdraw, Task Center, Wallet, Deposit, Withdraw, Rebate, VIP, Profit, Deposit & Withdrawal, Transaction Record, Bank Card Management, Bet History, Game Result, Language Selection, Join us\n\n\u001b[2mexpect(\u001b[22m\u001b[31mreceived\u001b[39m\u001b[2m).\u001b[22mtoBe\u001b[2m(\u001b[22m\u001b[32mexpected\u001b[39m\u001b[2m) // Object.is equality\u001b[22m\n\nExpected: \u001b[32m0\u001b[39m\nReceived: \u001b[31m18\u001b[39m\n    at C:\\Users\\luekc\\Desktop\\playwright_UI-master\\tests\\Q8\\Q8UItest.spec.js:1977:90",
        "rawStatus": "failed",
        "tags": [],
        "type": "e2e",
        "filePath": "C:\\Users\\luekc\\Desktop\\playwright_UI-master\\tests\\Q8\\Q8UItest.spec.js",
        "retries": 0,
        "flaky": false,
        "suite": "Q8\\Q8UItest.spec.js > @WAP Q8 測試"
      },
      {
        "name": "檢查個人頁icon圖片(EN)",
        "status": "failed",
        "duration": 17969,
        "start": 1723018647,
        "stop": 1723018665,
        "message": "Error: \u001b[2mexpect(\u001b[22m\u001b[31mreceived\u001b[39m\u001b[2m).\u001b[22mtoBe\u001b[2m(\u001b[22m\u001b[32mexpected\u001b[39m\u001b[2m) // Object.is equality\u001b[22m\n\nExpected: \u001b[32mtrue\u001b[39m\nReceived: \u001b[31mfalse\u001b[39m",
        "trace": "Error: \u001b[2mexpect(\u001b[22m\u001b[31mreceived\u001b[39m\u001b[2m).\u001b[22mtoBe\u001b[2m(\u001b[22m\u001b[32mexpected\u001b[39m\u001b[2m) // Object.is equality\u001b[22m\n\nExpected: \u001b[32mtrue\u001b[39m\nReceived: \u001b[31mfalse\u001b[39m\n    at C:\\Users\\luekc\\Desktop\\playwright_UI-master\\tests\\Q8\\Q8UItest.spec.js:2065:32",
        "rawStatus": "failed",
        "tags": [],
        "type": "e2e",
        "filePath": "C:\\Users\\luekc\\Desktop\\playwright_UI-master\\tests\\Q8\\Q8UItest.spec.js",
        "retries": 0,
        "flaky": false,
        "suite": "Q8\\Q8UItest.spec.js > @WAP Q8 測試"
      },
      {
        "name": "檢查About Luk gu(EN)",
        "status": "failed",
        "duration": 100000,
        "start": 1723018684,
        "stop": 1723018784,
        "rawStatus": "timedOut",
        "tags": [],
        "type": "e2e",
        "filePath": "C:\\Users\\luekc\\Desktop\\playwright_UI-master\\tests\\Q8\\Q8UItest.spec.js",
        "retries": 0,
        "flaky": false,
        "suite": "Q8\\Q8UItest.spec.js > @WAP Q8 測試"
      },
      {
        "name": "檢查遊戲開啟(EN)",
        "status": "failed",
        "duration": 100012,
        "start": 1723018789,
        "stop": 1723018889,
        "rawStatus": "timedOut",
        "tags": [],
        "type": "e2e",
        "filePath": "C:\\Users\\luekc\\Desktop\\playwright_UI-master\\tests\\Q8\\Q8UItest.spec.js",
        "retries": 0,
        "flaky": false,
        "suite": "Q8\\Q8UItest.spec.js > @WAP Q8 測試"
      },
      {
        "name": "檢查 关於 Betone",
        "status": "failed",
        "duration": 100472,
        "start": 1723017440,
        "stop": 1723017541,
        "rawStatus": "timedOut",
        "tags": [],
        "type": "e2e",
        "filePath": "C:\\Users\\luekc\\Desktop\\playwright_UI-master\\tests\\SG\\SGUItest.spec.js",
        "retries": 0,
        "flaky": false,
        "suite": "SG\\SGUItest.spec.js > @WAP SG 測試"
      },
      {
        "name": "檢查 About Betone(EN)",
        "status": "failed",
        "duration": 100169,
        "start": 1723017683,
        "stop": 1723017783,
        "rawStatus": "timedOut",
        "tags": [],
        "type": "e2e",
        "filePath": "C:\\Users\\luekc\\Desktop\\playwright_UI-master\\tests\\SG\\SGUItest.spec.js",
        "retries": 0,
        "flaky": false,
        "suite": "SG\\SGUItest.spec.js > @WAP SG 測試"
      },
      {
        "name": "檢查 Mengenai Bet One(MY)",
        "status": "failed",
        "duration": 100006,
        "start": 1723017851,
        "stop": 1723017951,
        "rawStatus": "timedOut",
        "tags": [],
        "type": "e2e",
        "filePath": "C:\\Users\\luekc\\Desktop\\playwright_UI-master\\tests\\SG\\SGUItest.spec.js",
        "retries": 0,
        "flaky": false,
        "suite": "SG\\SGUItest.spec.js > @WAP SG 測試"
      },
      {
        "name": "檢查 Acerca de Castillo",
        "status": "passed",
        "duration": 64502,
        "start": 1723017441,
        "stop": 1723017505,
        "rawStatus": "passed",
        "tags": [],
        "type": "e2e",
        "filePath": "C:\\Users\\luekc\\Desktop\\playwright_UI-master\\tests\\TK\\TKUItest.spec.js",
        "retries": 0,
        "flaky": false,
        "suite": "TK\\TKUItest.spec.js > @WAP TK 測試"
      },
      {
        "name": "检查 About Castillo(EN)",
        "status": "passed",
        "duration": 26540,
        "start": 1723017529,
        "stop": 1723017555,
        "rawStatus": "passed",
        "tags": [],
        "type": "e2e",
        "filePath": "C:\\Users\\luekc\\Desktop\\playwright_UI-master\\tests\\TK\\TKUItest.spec.js",
        "retries": 0,
        "flaky": false,
        "suite": "TK\\TKUItest.spec.js > @WAP TK 測試"
      },
      {
        "name": "rich88",
        "status": "failed",
        "duration": 1135200,
        "start": 1723017561,
        "stop": 1723018696,
        "message": "Error: \u001b[2mexpect(\u001b[22m\u001b[31mreceived\u001b[39m\u001b[2m).\u001b[22mtoBe\u001b[2m(\u001b[22m\u001b[32mexpected\u001b[39m\u001b[2m) // Object.is equality\u001b[22m\n\nExpected: \u001b[32m0\u001b[39m\nReceived: \u001b[31m99\u001b[39m",
        "trace": "Error: \u001b[2mexpect(\u001b[22m\u001b[31mreceived\u001b[39m\u001b[2m).\u001b[22mtoBe\u001b[2m(\u001b[22m\u001b[32mexpected\u001b[39m\u001b[2m) // Object.is equality\u001b[22m\n\nExpected: \u001b[32m0\u001b[39m\nReceived: \u001b[31m99\u001b[39m\n    at C:\\Users\\luekc\\Desktop\\playwright_UI-master\\tests\\TK\\TKUItest.spec.js:403:35",
        "rawStatus": "failed",
        "tags": [],
        "type": "e2e",
        "filePath": "C:\\Users\\luekc\\Desktop\\playwright_UI-master\\tests\\TK\\TKUItest.spec.js",
        "retries": 0,
        "flaky": false,
        "suite": "TK\\TKUItest.spec.js > @WAP TK 測試 > 遊戲場館測試"
      },
      {
        "name": "登入頁檢查",
        "status": "passed",
        "duration": 36611,
        "start": 1723017440,
        "stop": 1723017477,
        "rawStatus": "passed",
        "tags": [],
        "type": "e2e",
        "filePath": "C:\\Users\\luekc\\Desktop\\playwright_UI-master\\tests\\VN\\VNUItest.spec.js",
        "retries": 0,
        "flaky": false,
        "suite": "VN\\VNUItest.spec.js > @WAP VN 測試"
      },
      {
        "name": "註冊頁檢查",
        "status": "passed",
        "duration": 71999,
        "start": 1723017491,
        "stop": 1723017563,
        "rawStatus": "passed",
        "tags": [],
        "type": "e2e",
        "filePath": "C:\\Users\\luekc\\Desktop\\playwright_UI-master\\tests\\VN\\VNUItest.spec.js",
        "retries": 0,
        "flaky": false,
        "suite": "VN\\VNUItest.spec.js > @WAP VN 測試"
      },
      {
        "name": "檢查 Giới thiệu về RG88",
        "status": "passed",
        "duration": 24598,
        "start": 1723017572,
        "stop": 1723017596,
        "rawStatus": "passed",
        "tags": [],
        "type": "e2e",
        "filePath": "C:\\Users\\luekc\\Desktop\\playwright_UI-master\\tests\\VN\\VNUItest.spec.js",
        "retries": 0,
        "flaky": false,
        "suite": "VN\\VNUItest.spec.js > @WAP VN 測試"
      },
      {
        "name": "遊戲icon",
        "status": "passed",
        "duration": 76736,
        "start": 1723017612,
        "stop": 1723017688,
        "rawStatus": "passed",
        "tags": [],
        "type": "e2e",
        "filePath": "C:\\Users\\luekc\\Desktop\\playwright_UI-master\\tests\\VN\\VNUItest.spec.js",
        "retries": 0,
        "flaky": false,
        "suite": "VN\\VNUItest.spec.js > @WAP VN 測試"
      },
      {
        "name": "rich88",
        "status": "failed",
        "duration": 1702415,
        "start": 1723017719,
        "stop": 1723019421,
        "message": "Error: \u001b[2mexpect(\u001b[22m\u001b[31mreceived\u001b[39m\u001b[2m).\u001b[22mtoBe\u001b[2m(\u001b[22m\u001b[32mexpected\u001b[39m\u001b[2m) // Object.is equality\u001b[22m\n\nExpected: \u001b[32m0\u001b[39m\nReceived: \u001b[31m94\u001b[39m",
        "trace": "Error: \u001b[2mexpect(\u001b[22m\u001b[31mreceived\u001b[39m\u001b[2m).\u001b[22mtoBe\u001b[2m(\u001b[22m\u001b[32mexpected\u001b[39m\u001b[2m) // Object.is equality\u001b[22m\n\nExpected: \u001b[32m0\u001b[39m\nReceived: \u001b[31m94\u001b[39m\n    at C:\\Users\\luekc\\Desktop\\playwright_UI-master\\tests\\VN\\VNUItest.spec.js:455:35",
        "rawStatus": "failed",
        "tags": [],
        "type": "e2e",
        "filePath": "C:\\Users\\luekc\\Desktop\\playwright_UI-master\\tests\\VN\\VNUItest.spec.js",
        "retries": 0,
        "flaky": false,
        "suite": "VN\\VNUItest.spec.js > @WAP VN 測試 > 遊戲場館測試"
      }
    ]
  }
}
